AUTHORS.rst
HISTORY.rst
LICENSE
MANIFEST.in
README.rst
setup.cfg
setup.py
django_emailmessagetemplates.egg-info/PKG-INFO
django_emailmessagetemplates.egg-info/SOURCES.txt
django_emailmessagetemplates.egg-info/dependency_links.txt
django_emailmessagetemplates.egg-info/not-zip-safe
django_emailmessagetemplates.egg-info/requires.txt
django_emailmessagetemplates.egg-info/top_level.txt
emailmessagetemplates/__init__.py
emailmessagetemplates/admin.py
emailmessagetemplates/conf.py
emailmessagetemplates/fields.py
emailmessagetemplates/forms.py
emailmessagetemplates/models.py
emailmessagetemplates/tests.py
emailmessagetemplates/utils.py
emailmessagetemplates/migrations/0001_initial.py
emailmessagetemplates/migrations/__init__.py
emailmessagetemplates/static/emailmessagetemplates/js/admin.js