Metadata-Version: 1.1
Name: django-emailmessagetemplates
Version: 0.1.3
Summary: A Django app that allows users to edit email content with an easy-to-integrate developer API.
Home-page: https://github.com/mcoconnor/django-emailmessagetemplates
Author: Michael OConnor
Author-email: michael@mcoconnor.net
License: BSD
Keywords: django,email,template
Platform: UNKNOWN
Classifier: Development Status :: 4 - Beta
Classifier: Framework :: Django
Classifier: Intended Audience :: Developers
Classifier: License :: OSI Approved :: BSD License
Classifier: Natural Language :: English
Classifier: Programming Language :: Python :: 2
Classifier: Programming Language :: Python :: 2.7
Classifier: Operating System :: OS Independent
Classifier: Environment :: Web Environment
